PrettyTextTestRunner/__init__.py
PrettyTextTestRunner/textTable.py
PrettyTextTestRunner-0.1.1.dist-info/LICENSE
PrettyTextTestRunner-0.1.1.dist-info/METADATA
PrettyTextTestRunner-0.1.1.dist-info/NOTICE.md
PrettyTextTestRunner-0.1.1.dist-info/WHEEL
PrettyTextTestRunner-0.1.1.dist-info/top_level.txt
PrettyTextTestRunner-0.1.1.dist-info/RECORD
