Metadata-Version: 2.1
Name: PrettyTextTestRunner
Version: 0.1.1
Summary: Rich drop-in replacement for unittest.TextTestRunner
Home-page: https://github.com/villagertech/PyPrettyTextTestRunner
Author: Rob MacKinnon
Author-email: rome@villagertech.com
License: UNKNOWN
Platform: UNKNOWN
Classifier: Programming Language :: Python :: 3
Classifier: License :: OSI Approved :: MIT License
Classifier: Operating System :: OS Independent
Requires-Python: >=3.2
